universal_video_downloader/__init__.py
universal_video_downloader/cli.py
universal_video_downloader/gui.py
universal_video_downloader-1.0.0.dist-info/METADATA
universal_video_downloader-1.0.0.dist-info/WHEEL
universal_video_downloader-1.0.0.dist-info/entry_points.txt
universal_video_downloader-1.0.0.dist-info/top_level.txt
universal_video_downloader-1.0.0.dist-info/RECORD
