Metadata-Version: 2.4
Name: universal-video-downloader
Version: 1.0.0
Summary: Download videos and audio from YouTube, TikTok, Instagram, Facebook, X, Reddit, Vimeo, DailyMotion, and more
Home-page: https://github.com/Aarif5856/UniversalVideoDownloader
Author: Aarif5856
Author-email: Aarif5856 <your-email@example.com>
License: MIT
Project-URL: Homepage, https://github.com/Aarif5856/UniversalVideoDownloader
Project-URL: Repository, https://github.com/Aarif5856/UniversalVideoDownloader
Project-URL: Issues, https://github.com/Aarif5856/UniversalVideoDownloader/issues
Keywords: video,downloader,youtube,tiktok,instagram
Classifier: Development Status :: 4 - Beta
Classifier: Intended Audience :: End Users/Desktop
Classifier: License :: OSI Approved :: MIT License
Classifier: Operating System :: OS Independent
Classifier: Programming Language :: Python :: 3
Classifier: Programming Language :: Python :: 3.8
Classifier: Programming Language :: Python :: 3.9
Classifier: Programming Language :: Python :: 3.10
Classifier: Programming Language :: Python :: 3.11
Classifier: Programming Language :: Python :: 3.12
Classifier: Topic :: Multimedia :: Video
Requires-Python: >=3.8
Requires-Dist: yt-dlp>=2023.1.6
Requires-Dist: PyQt5>=5.15.0
Requires-Dist: requests>=2.28.0
Requires-Dist: tkinterdnd2>=0.2.1
Provides-Extra: dev
Requires-Dist: pytest>=7.0; extra == "dev"
Requires-Dist: black>=22.0; extra == "dev"
Requires-Dist: flake8>=4.0; extra == "dev"
Dynamic: author
Dynamic: home-page
Dynamic: requires-python
